pymq/__init__.py
pymq/core.py
pymq/exceptions.py
pymq/json.py
pymq/typing.py
pymq/provider/__init__.py
pymq/provider/aws.py
pymq/provider/base.py
pymq/provider/ipc.py
pymq/provider/redis.py
pymq/provider/simple.py
pymq-0.6.2.dist-info/LICENSE
pymq-0.6.2.dist-info/METADATA
pymq-0.6.2.dist-info/WHEEL
pymq-0.6.2.dist-info/top_level.txt
pymq-0.6.2.dist-info/RECORD
