Metadata-Version: 2.1
Name: pymq
Version: 0.6.2
Summary: A simple message-oriented middleware library built for Python IPC across machine boundaries
Home-page: https://github.com/thrau/pymq
Author: Thomas Rausch
Author-email: thomas@thrau.at
License: MIT
Platform: UNKNOWN
Classifier: Development Status :: 4 - Beta
Classifier: License :: OSI Approved :: MIT License
Classifier: Operating System :: OS Independent
Classifier: Programming Language :: Python :: 3
Classifier: Programming Language :: Python :: 3.6
Classifier: Programming Language :: Python :: 3.7
Classifier: Programming Language :: Python :: 3.8
Classifier: Programming Language :: Python :: 3.9
Classifier: Programming Language :: Python :: 3.10
Classifier: Topic :: System :: Networking
License-File: LICENSE
Provides-Extra: aws
Requires-Dist: boto3 ; extra == 'aws'
Provides-Extra: full
Requires-Dist: redis (>=3.2.1) ; extra == 'full'
Requires-Dist: posix-ipc (==1.0.4) ; extra == 'full'
Requires-Dist: boto3 ; extra == 'full'
Provides-Extra: ipc
Requires-Dist: posix-ipc (==1.0.4) ; extra == 'ipc'
Provides-Extra: redis
Requires-Dist: redis (>=3.2.1) ; extra == 'redis'
Provides-Extra: test
Requires-Dist: coverage[toml] (>=5.0) ; extra == 'test'
Requires-Dist: pytest-cov (>=2.7.1) ; extra == 'test'
Requires-Dist: coveralls ; extra == 'test'
Requires-Dist: black (>=22.1) ; extra == 'test'
Requires-Dist: isort (>=5.10) ; extra == 'test'
Requires-Dist: pytest (>=7.0) ; extra == 'test'
Requires-Dist: pytest-timeout (>=2.1) ; extra == 'test'
Requires-Dist: localstack (>=0.14) ; extra == 'test'
Requires-Dist: redislite (>=5.0.124623) ; extra == 'test'
